odoo/addons/module_change_auto_install/README.rst
odoo/addons/module_change_auto_install/__init__.py
odoo/addons/module_change_auto_install/__manifest__.py
odoo/addons/module_change_auto_install/patch.py
odoo/addons/module_change_auto_install/i18n/ca.po
odoo/addons/module_change_auto_install/i18n/fr.po
odoo/addons/module_change_auto_install/i18n/it.po
odoo/addons/module_change_auto_install/i18n/module_change_auto_install.pot
odoo/addons/module_change_auto_install/readme/CONFIGURE.md
odoo/addons/module_change_auto_install/readme/CONTRIBUTORS.md
odoo/addons/module_change_auto_install/readme/DESCRIPTION.md
odoo/addons/module_change_auto_install/readme/DEVELOP.md
odoo/addons/module_change_auto_install/readme/INSTALL.md
odoo/addons/module_change_auto_install/static/description/icon.png
odoo/addons/module_change_auto_install/static/description/index.html
odoo/addons/module_change_auto_install/tests/__init__.py
odoo/addons/module_change_auto_install/tests/test_module.py
odoo/addons/module_change_auto_install/tests/test_patch.py
odoo_addon_module_change_auto_install-19.0.1.0.0.2.dist-info/METADATA
odoo_addon_module_change_auto_install-19.0.1.0.0.2.dist-info/WHEEL
odoo_addon_module_change_auto_install-19.0.1.0.0.2.dist-info/top_level.txt
odoo_addon_module_change_auto_install-19.0.1.0.0.2.dist-info/RECORD
