Metadata-Version: 2.1
Name: odoo-addon-module_change_auto_install
Version: 19.0.1.0.0.2
Requires-Dist: odoo==19.0.*
Summary: Customize auto installables modules by configuration
Home-page: https://github.com/OCA/server-tools
License: AGPL-3
Author: GRAP, Odoo Community Association (OCA)
Author-email: support@odoo-community.org
Classifier: Programming Language :: Python
Classifier: Framework :: Odoo
Classifier: Framework :: Odoo :: 19.0
Classifier: License :: OSI Approved :: GNU Affero General Public License v3
